opentelemetry_container_distro/__init__.py
opentelemetry_container_distro/py.typed
opentelemetry_container_distro-0.2.0.dist-info/LICENSE
opentelemetry_container_distro-0.2.0.dist-info/METADATA
opentelemetry_container_distro-0.2.0.dist-info/WHEEL
opentelemetry_container_distro-0.2.0.dist-info/entry_points.txt
opentelemetry_container_distro-0.2.0.dist-info/top_level.txt
opentelemetry_container_distro-0.2.0.dist-info/RECORD
