Metadata-Version: 2.1
Name: opentelemetry-container-distro
Version: 0.2.0
Summary: An OpenTelemetry distro which automatically discovers container attributes
Home-page: https://github.com/chrisguidry/opentelemetry-container-distro
Author: Chris Guidry
Author-email: chris@theguidrys.us
Project-URL: Bug Tracker, https://github.com/chrisguidry/opentelemetry-container-distro/issues
Classifier: Programming Language :: Python :: 3
Classifier: License :: OSI Approved :: MIT License
Requires-Python: >=3.8
License-File: LICENSE
Requires-Dist: opentelemetry-api
Requires-Dist: opentelemetry-exporter-otlp
Requires-Dist: opentelemetry-instrumentation
Requires-Dist: opentelemetry-resourcedetector-docker (>=0.3.0)
Requires-Dist: opentelemetry-resourcedetector-kubernetes (>=0.2.1)
Requires-Dist: opentelemetry-resourcedetector-process (>=0.1.1)
Requires-Dist: opentelemetry-sdk
Provides-Extra: dev
Requires-Dist: black ; extra == 'dev'
Requires-Dist: build ; extra == 'dev'
Requires-Dist: flake8 ; extra == 'dev'
Requires-Dist: flake8-black ; extra == 'dev'
Requires-Dist: isort ; extra == 'dev'
Requires-Dist: mypy ; extra == 'dev'
Requires-Dist: pre-commit ; extra == 'dev'
Requires-Dist: pytest ; extra == 'dev'
Requires-Dist: pytest-cov ; extra == 'dev'
Requires-Dist: pytest-xdist ; extra == 'dev'
Requires-Dist: twine ; extra == 'dev'
Requires-Dist: types-setuptools ; extra == 'dev'
